reporter/__init__.py
reporter/main.py
reporter/server.py
reporter/report_web/app.js
reporter/report_web/index.html
reporter/report_web/index.js
reporter/report_web/style.css
reporter/report_web/utils/log.js
fsr-0.1.45.dist-info/LICENSE
fsr-0.1.45.dist-info/METADATA
fsr-0.1.45.dist-info/WHEEL
fsr-0.1.45.dist-info/entry_points.txt
fsr-0.1.45.dist-info/top_level.txt
fsr-0.1.45.dist-info/RECORD
